Workbook

Sheet SDG Proposal
A1: Life Event | B1: Nº Seq | C1: Procedure | D1: Expected output subject to an assessment of the application by the competent authority in accordance with their national law, where relevant
A2: Birth | B2: 1 | C2: Requesting proof of registration of birth | D2: Proof of registration of birth or birth certificate
A3: Residence | B3: 2 | C3: Requesting proof of residence | D3: Confirmation of registration at the current address
A4: Studying | B4: 3 | C4: Applying for a tertiary education study financing, such as study grants and loans from a public body or institution | D4: Decision on the application for financing or acknowledgement of receipt
B5: 4 | C5: Submiting an initial application for admission in public higher education institution | D5: Confirmation of the receipt of application
A6: Working | B6: 5 | C6: Request for determination of applicable legislation in accordance with Title II of Regulation (EC) No 883/200429 | D6: Decision on applicable legislation
B7: 6 | C7: Notifying changes in personal or professional circumstances of the person receiving socialsecurity benefits, relevant for such benefits | D7: Confirmation of receipt of notification of change
B8: 7 | C8: Application for European Health Insurance Card (EHIC) | D8: European Health Insurance Card (EHIC)
B9: 8 | C9: Requesting academic recognition of diplomas, certificates or other proof of studies or courses | D9: Decision on the request for recognition
B10: 9 | C10: Submitting an income tax declaration | D10: Confirmation of the receipt of the declaration
A11: Moving | B11: 10 | C11: Registering a change of address | D11: Confirmation of the deregistration at the previous address and of the registration of the new address
B12: 11 | C12: Registering a motor vehicle originating from or already registered in an EU Member State, in standard procedures30 | D12: Proof of registration of a motor vehicle
B13: 12 | C13: Obtaining stickers for the use of the national road infrastructure: toll or vignette issued by a public body or institution | D13: Receipt of toll sticker or vignette or other proof of payment
B14: 13 | C14: Obtaining emission stickers issued by a public body or institution | D14: Receipt of emission sticker or other proof of payment
A15: Retiring | B15: 14 | C15: Claiming pension and pre-retirement benefits from compulsory schemes | D15: Confirmation of the receipt of the claim or decision regarding the claim for a pension or pre-retirement benefits
B16: 15 | C16: Requesting information on the data related to pension from compulsory schemes | D16: Statement of personal pension data
A17: Starting a business | B17: 16 | C17: Notification of business activity, permissions of business activity, changes of business activity and the termination of a business activity not involving insolvency or liquidation procedures, excluding the initial registration of a business activity with the business register and excluding procedures concerning the constitution of or any subsequent filing by companies or firms within the meaning of the second paragraph of Article 54 TFEU | D17: Confirmation of the receipt of notification or change, or of the request for permission of business activity
B18: 17 | C18: Registration of an employer (a natural person) with compulsory pension and insurance schemes | D18: Confirmation of registration or social security registration number
B19: 18 | C19: Registration of employees with compulsory pension and insurance schemes | D19: Confirmation of registration or social security registration number
B20: 19 | C20: Submitting a corporate tax declaration | D20: Confirmation of the receipt of the declaration
A21: Doing business | B21: 20 | C21: Notification to the social security schemes of the end of contract with an employee, excluding procedures for the collective termination of employee contracts | D21: Confirmation of the receipt of the notification
B22: 21 | C22: Payment of social contributions for employees | D22: Receipt or other form of confirmation of payment of social contributions for employees

Sheet ES-PT Proposal
A1: Service Id. | B1: SDG Life Event | C1: Nº Seq SDG | D1: ES Service | E1: Comments | F1: PORTUGUESE CATALOGUE | G1: PORTUGUESE CATALOGUE ID | H1: Nome serviço | I1: =A1 -> Service Id.
A2: 1 | B2: Birth | C2: 1 | D2: Bithday Certificate | F2: YES | G2: CES:SRV:000000041 | H2: Pedir a certidão de nascimento | I2: =A2 -> 1
A3: =A2+1 -> 2 | B3: Residence | C3: 2 | D3: Residence Certificate for Europeans | F3: YES | G3: CES:SRV:000001775 | H3: Pedir o certificado de residência permanente para cidadão da UE/EEE/Suíça | I3: =A3 -> 2
A4: =A3+1 -> 3 | B4: Studing | C4: 3 | D4: Study aids to produce doctoral thesis | F4: NO | G4: - | H4: - | I4: =A4 -> 3
A5: =A4+1 -> 4 | B5: Studing | C5: 4 | D5: Application for Grade or Master studies in Granada University | F5: NO | G5: - | H5: - | I5: =A5 -> 4
A6: =A5+1 -> 5 | B6: Working | C6: 8 | D6: Homologation of university degrees and recognition of qualifications | F6: NO | G6: - | H6: - | I6: =A6 -> 5
A7: =A6+1 -> 6 | B7: Working | C7: 6 | D7: Modification of data about pension | F7: NO | G7: - | H7: - | I7: =A7 -> 6
A8: =A7+1 -> 7 | B8: Working | C8: 7 | D8: Application for European Health Insurance Card | F8: YES | G8: CES:SRV:000001543 | H8: Pedir o Cartão Europeu de Seguro de Doença da Segurança Social | I8: =A8 -> 7
A9: =A8+1 -> 8 | B9: Moving | C9: 10 | D9: Communication of change of address | F9: YES | G9: CES:SRV:000000462 | H9: Alterar a morada no Cartão de Cidadão | I9: =A9 -> 8
A10: =A9+1 -> 9 | B10: Retiring | C10: 15 | D10: Claiming retirement pension | F10: YES | G10: CES:SRV:000000867 | H10: Obter informações sobre a pensão social de velhice | I10: =A10 -> 9
A11: =A10+1 -> 10 | B11: Starting B. | C11: 16 | D11: Instalación de situados para ejercer la venta ambulante | E11: ES: City council of Madrid | F11: YES | G11: CES:SRV:000002460 | H11: Feirante ou vendedor ambulante - acesso à atividade | I11: =A11 -> 10
A12: =A11+1 -> 11 | B12: Starting B. | C12: 16 | D12: Import, export, manufacturing of non-registered medicines | F12: NO | G12: - | H12: - | I12: =A12 -> 11
A13: =A12+1 -> 12 | B13: Starting B. | C13: 16 | D13: Authorization request for operating Fish Farms or Aquaculture Facilities | E13: ES: Andalucía Autonomous Region | F13: YES | G13: CES:SRV:000004747 | H13: Aquicultura - título de atividade aquícola - águas marinhas | I13: =A13 -> 12
A14: =A13+1 -> 13 | B14: Starting B. | C14: 16 | D14: Authorization of commercial license to large commercial establishments and shopping centers. | E14: ES: Canarias Autonomous Region | F14: YES | G14: CES:SRV:000002276 | H14: Comércio a retalho em grande superfície comercial inserida em conjunto comercial - exploração de estabelecimento | I14: =A14 -> 13
A15: =A14+1 -> 14 | B15: Starting B. | C15: 16 | D15: Registry for startup of a guesthouse activity | E15: ES: Baleares Autonomous Region | F15: YES | G15: CES:SRV:000002072 | H15: Alojamento local - registo da atividade | I15: =A15 -> 14
A16: =A15+1 -> 15 | B16: Starting B. | C16: 16 | D16: Communication of cessation of activity of a non-hotel tourist accommodation establishment | E16: ES: Cantabria Autonomous Region | F16: YES | G16: CES:SRV:000002071 | H16: Alojamento local - cessação da atividade | I16: =A16 -> 15
A17: =A16+1 -> 16 | B17: Starting B. | C17: 16 | D17: Declaration of prices and services of tourist accommodation | E17: ES: Cataluña Autonomous Region | F17: NO | G17: - | H17: - | I17: =A17 -> 16
A18: =A17+1 -> 17 | B18: Starting B. | C18: 16 | D18: Start of activity of catering facility | E18: ES: Madrid Autonomous Region | F18: YES | G18: CES:SRV:000003002 | H18: Restauração e bebidas - exploração de estabelecimento | I18: =A18 -> 17
A19: =A18+1 -> 18 | B19: Starting B. | C19: 16 | D19: Register of Real Estate Agents of Catalonia | E19: ES: Cataluña Autonomous Region | F19: YES | G19: CES:SRV:000002668 | H19: Mediação imobiliária - licença para o exercício da atividade | I19: =A19 -> 18
A20: =A19+1 -> 19 | B20: Starting B. | C20: 16 | D20: Clearance sales communication | E20: ES: Castilla la Mancha Autonomous Region | F20: YES | G20: CES:SRV:000002953 | H20: Realização de saldos - comunicação | I20: =A20 -> 19
A21: =A20+1 -> 20 | B21: Starting B. | C21: 16 | D21: Registration in the Special Register of Repair Shops for motor vehicles and their equipment and components | E21: ES: La Rioja Autonomous Region | F21: YES | G21: CES:SRV:000002637 | H21: Manutenção e reparação de veículos automóveis, motociclos e ciclomotores - exploração de oficina | I21: =A21 -> 20
A22: =A21+1 -> 21 | B22: Starting B. | C22: 16 | D22: Registration in the Official Register of tanning centers | E22: ES: Extremadura Autonomous Region | F22: YES | G22: CES:SRV:000002210 | H22: Centro de bronzeamento artificial – exploração de estabelecimento | I22: =A22 -> 21
A23: =A22+1 -> 22 | B23: Starting B. | C23: 16 | D23: Sanitary authorization for tattoo and piercing establishments | E23: ES: Murcia Autonomous Region | F23: YES | G23: CES:SRV:000002857 | H23: Piercings e tatuagens - exploração de estabelecimento | I23: =A23 -> 22
A24: =A23+1 -> 23 | B24: Starting B. | C24: 16 | D24: Change of activity in business premises | E24: ES: Madrid Autonomous Region | F24: YES | G24: - | H24: - | I24: =A24 -> 23
... A26: =A25+1 -> 25 | B26: Starting B. | C26: 16 | D26: Business licence for large retail trade establishment | E26: ES: La Rioja Autonomous Region | F26: YES | G26: CES:SRV:000002276 | H26: Comércio a retalho em grande superfície comercial inserida em conjunto comercial - exploração de estabelecimento | I26: =A26 -> 25
A27: =A26+1 -> 26 | B27: Starting B. | C27: 17 | D27: Employer registration in Social Security with tax account code | F27: NO | G27: - | H27: - | I27: =A27 -> 26
A28: =A27+1 -> 27 | B28: Starting B. | C28: 18 | D28: Registration of workers in the General Scheme | F28: NO | G28: - | H28: - | I28: =A28 -> 27
A29: =A28+1 -> 28 | B29: Starting B. | C29: 19 | D29: Submmition of Corporate Tax (Model 200) | F29: NO | G29: - | H29: - | I29: =A29 -> 28
A30: =A29+1 -> 29 | B30: Doing B. | C30: 20 | D30: Withdrawal of workers in the General Scheme | F30: NO | G30: - | H30: - | I30: =A30 -> 29
A31: =A30+1 -> 30 | B31: Doing B. | C31: 21 | D31: Payment of social security contributions for workers in the General Scheme | F31: NO | G31: - | H31: - | I31: =A31 -> 30

Sheet ES_PS-es
B1: Public Service | H1: Public Organization | J1: Channel | L1: Event | P1: Other
A2: Nº in Proposal | B2: Identifier | C2: Name | D2: Description | E2: Keyword | F2: Language | G2: Thematic Area | H2: Preferred Label | I2: Spatial Code | J2: Identifier | K2: Type | L2: Id. | M2: Name | N2: Class | O2: Type | P2: eId Systems
A3: ='ES-PT Proposal'!A2 -> 1 | B3: 109000 | C3: Certificado de nacimiento | D3: El certificado de nacimiento es el documento expedido por el Encargado del Registro Civil o Consular correspondiente, que da fe del hecho del nacimiento, fecha en que tuvo lugar, del sexo, y en su caso, de la hora en que se produjo el nacimiento y de la filiación del inscrito. Asímismo, podrán expedirse certificaciones electrónicas de nacimiento con sello electrónico de la Dirección General de los Registros y del Notariado a partir de los datos contenidos en la base central de datos de las personas inscritas en los Registros Civiles. ¿Cómo? Entra en la Sede Electrónica del Ministerio de Justicia(Abre en nueva ventana) y accede al Certificado de nacimiento. Puedes elegir entre recibir el certificado por correo ordinario al domicilio indicado en la solicitud o recogerlo en el Registro Civil correspondiente siempre que lo hayas indicado expresamente. En este caso será el propio Registro Civil el que te indicará a partir de qué fecha podrás recogerlo. | E3: nacimiento, certificado, ministerio de justicia, encargado del registro civil, consular, dirección general de los registros, notariado, registros civiles, sede electrónica del ministerio de justicia, registro civil | F3: Spanish | G3: Justicia | H3: Ministerio de Justicia | I3: ESP | J3: http://www.mjusticia.gob.es/cs/Satellite/Portal/es/servicios-ciudadano/tramites-gestiones-personales/certificadocertificacion | K3: Tramitación Electrónica | L3: http://administracion.gob.es/pagFront/tramites/miVidaEnTramites/listadoHechosVitales/previsualizacionHechoVital.htm?idHechoVital=21 | M3: Guia de trámites para tener un hijo | N3: Life Event | O3: Tener un hijo | P3: Certificado electrónico, DNI electrónico,Otros
A4: ='ES-PT Proposal'!A3 -> 2 | B4: 994455 | C4: Certificado de residente | D4: Acreditar ante otros organismos periodos de residencia legal en España (se admite Registro Electrónico del Cuerpo Nacional de Policía ÚNICAMENTE para ciudadanos de Estados miembros de la Unión Europea, del Espacio Económico Europeo, Suiza y Principado de Andorra) | E4: residente, certificado, españa, registro electrónico del cuerpo nacional de policía únicamente, estados, unión europea, espacio económico europeo, suiza, principado de andorra | F4: Spanish | G4: Ciudadanía y nacionalidad | H4: Ministerio del Interior | I4: ESP | J4: https://sede.policia.gob.es/portalCiudadano/extranjeria/pr_cer_residen.html | K4: Tramitación Electrónica | P4: Certificado electrónico
A5: ='ES-PT Proposal'!A8 -> 7 | B5: 203557 | C5: Solicitud Tarjeta Sanitaria Europea | D5: Solicitud de la Tarjeta Sanitaria Europea (TSE). La TSE es el documento que acredita el derecho a acceder a los servicios públicos de salud durante las estancias temporales en los Estado Miembro de la Unión Europea, Espacio Económico Europeo y Suiza, en las mismas condiciones y con la misma extensión que los ciudadanos del país que esté visitando.Esta tarjeta es personal e intransferible.La TSE tendrá una vigencia de dos años tanto para los mutualistas como para los beneficiarios | E5: solicitud tarjeta sanitaria europea, la tarjeta sanitaria europea, tse, estado miembro de la unión europea, espacio económico europeo, suiza | F5: Spanish | G5: Salud | H5: Mutualidad General de Funcionarios Civiles del Estado (MUFACE) | I5: ESP | J5: https://sede.muface.gob.es | K5: Tramitación Electrónica | P5: Usuario y contraseña, Certificado electrónico,DNI electrónico
A6: ='ES-PT Proposal'!A9 -> 8 | B6: 200265 | C6: Servicio de Comunicación del Cambio de Domicilio | D6: Este servicio permite que el ciudadano, una vez realizado el empadronamiento, pueda comunicar a distintos organismos de la Administración General del Estado, como Dirección General de Tráfico, Agencia Tributaria, Dirección General de la Policía y Seguridad Social entre otros, su cambio de domicilio sin tener que ir presencialmente a cada uno de ellos. | E6: servicio de comunicación del cambio de domicilio, administración general del estado, dirección general de tráfico, agencia tributaria, dirección general de la policía, seguridad social | F6: Spanish | G6: * Relaciones del ciudadano, empresa o empleado público con la Administración * Participación e iniciativa ciudadana | H6: S.Gral. de Administración Digital | I6: ESP | J6: https://cambiodomicilio.redsara.es/pcd/ | K6: Tramitación Electrónica | L6: http://administracion.gob.es/pagFront/tramites/miVidaEnTramites/listadoHechosVitales/previsualizacionHechoVital.htm?idHechoVital=103 | M6: Guia de trámites para comprar una vivienda | N6: Life Event | O6: Comprar una vivienda | P6: Certificado electrónico, DNI electrónico
A7: ='ES-PT Proposal'!A10 -> 9 | B7: 20650 | C7: Pensión de jubilación | D7: Accede a este servicio para solicitar la prestación económica de jubilación | E7: jubilación, pensión | F7: Spanish | G7: Pensiones | H7: Instituto Nacional de la Seguridad Social | I7: ESP | J7: https://sede.seg-social.gob.es/Sede_1/ServiciosenLinea/Ciudadanos/index.htm?ssUserText=131145 | K7: Tramitación Electrónica | P7: Certificado electrónico
A8: ='ES-PT Proposal'!A11 -> 10 | B8: 203508 | C8: Instalación de un puesto para el ejercicio de la venta no sedentaria en Mercados ocasionales instalados sobre el dominio público municipal | D8: La venta podrá realizarse en mercadillos periódicos u ocasionales, mercadillos de régimen singular, mercadillos sectoriales y enclaves aislados en la vía pública durante los periodos que señale cada autorización. | E8: situados, instalación, ejercer, venta, ambulante | F8: Spanish | G8: Medio ambiente | H8: Ayuntamiento de Madrid | I8: - no spatial code - | J8: https://sede.madrid.es/portal/site/tramites/menuitem.1f3361415fda829be152e15284f1a5a0/?vgnextoid=59628af352bed010VgnVCM1000000b205a0aRCRD&vgnextchannel=f47ea38813180210VgnVCM100000c90da8c0RCRD | K8: Descarga y envío | P8: N/A
A9: ='ES-PT Proposal'!A13 -> 12 | B9: 203888 | C9: Puesta en Funcionamiento de Piscifactorías o Instalaciones de Acuicultura: Autorización | D9: Obtener la autorización para la puesta en funcionamiento de piscifactorías o instalaciones de acuicultura continental con una capacidad inferior a las 500 toneladas. Está autorización debe de entenderse sin perjuicio de la concesión que deba obtenerse de la Administración Hidráulica (Agencia Andaluza del Agua o Confederación Hidrográfica del Guadalquivir). Si la instalación tiene una capacidad superior a las 500 toneladas se encuentra sometida a AAU (apartado 9.9 del Anexo I de la GICA). Las competencias en materia de acuicultura marina y de control zoosanitario corresponden a la Consejería competente en materia de agricultura y pesca. | E9: puesta, funcionamiento de piscifactorías, instalaciones de acuicultura, autorización, administración hidráulica, agencia andaluza del agua, confederación hidrográfica del guadalquivir, aau, anexo i de la gica, consejería | F9: Spanish | G9: Medio ambiente | H9: Junta de Andalucía | I9: ESP_CMA_ANDAL | J9: http://www.juntadeandalucia.es/haciendayadministracionpublica/ciudadania/web/guest/procedimientos | K9: Descarga y envío
A10: ='ES-PT Proposal'!A14 -> 13 | B10: 220359 | C10: Autorización de licencia comercial a grandes establecimientos comerciales y centros comerciales | D10: Autorizar la concesión de la licencia comercial para la instalación y apertura, ampliación de superficie útil de exposición y venta, el traslado o cambio de actividad a grandes establecimientos comerciales y centros comerciales. | E10: licencia, autorización, comercial, grandes, establecimientos, comerciales, centros | F10: Spanish | G10: Consumo | H10: Comunidad Autónoma de Canarias | I10: ESP_CMA_CANAR | J10: https://sede.gobcan.es/sede/tramites/2715 | K10: Descarga de formulario
A11: ='ES-PT Proposal'!A15 -> 14 | B11: 208249 | C11: Inscripción de inicio de actividad de establecimiento de alojamiento de hospedería | D11: Inscripción en el Registro General de Empresas, Actividades y Establecimientos Turísticos de las Illes Balears y en el Insular de Mallorca, de los establecimientos de alojamiento de hospedería que desarrollan su actividad en la isla de Mallorca.En el resto de islas, los órganos competentes serán los respectivos Consejos Insulares.Son establecimientos que forman parte de una iglesia, capilla o santuario y que destinan algunas de sus dependencias al servicio de alojamiento al público en general.Quedan excluidos de esta consideración los establecimientos de titularidad de las Administraciones Públicas o de entidades privadas el uso del cual este reservado a grupos de personas que deban cumplir determinados requisitos, como la pertenencia a una orden religiosa o similar y, en consecuencia, no se ofrece al público en general.Los titulares de la hospedería pueden tener un régimen de admisión y unas normas de comportamiento adecuados a los estatutos de su orden religiosa, que en todo caso se deberán poner en conocimiento de los posibles huéspedes de manera explícita antes de la contratación | E11: inicio, inscripción, actividad, establecimiento, alojamiento, hospedería, registro general de empresas, actividades, establecimientos turísticos de las illes balears, insular de mallorca | F11: Spanish | G11: Turismo, ocio y tiempo libre | H11: Gobierno de las Islas Baleares | I11: ESP_CMA_BALEAR | J11: https://www.caib.es/seucaib/es/tramites/tramite/2432054 | K11: Tramitación Electrónica
A12: ='ES-PT Proposal'!A16 -> 15 | B12: 215091 | C12: Comunicación de cese de actividad de un establecimiento de alojamiento turístico extrahotelero | D12: Comunicar a la Consejería competente en materia de turismo el cese de actividad de un establecimiento de alojamiento turístico extrahotelero. | E12: cese, comunicación, actividad, establecimiento, alojamiento, turístico, extrahotelero, consejería | F12: Spanish | G12: Turismo, ocio y tiempo libre | H12: Presidencia del Gobierno de Cantabria | I12: ESP_PR_CANTAB | J12: https://www.cantabria.es/tramites-web?codigo=IND-X-017 | K12: Descarga y envío
A13: ='ES-PT Proposal'!A18 -> 17 | B13: 203212 | C13: Inicio de Actividad de Establecimientos de Restauración | D13: Declaración responsable para el inicio de la actividad de los establecimientos turísticos de restauración en sus diversas modalidades (Restaurante, Cafeterías, Bares, Catering), así como sus posteriores modificaciones (cambios de titular, ceses de actividad, etc.) | E13: inicio de actividad de establecimientos de restauración, restaurante, cafeterías, bares, catering | F13: Spanish | G13: * Turismo, ocio y tiempo libre * Empresas | H13: Comunidad de Madrid | I13: ESP_CMA_MAD | J13: http://www.madrid.org/cs/Satellite?c=CM_Tramite_FA&cid=1142598088068&noMostrarML=true&pageid=1331802501637&pagename=PortalCiudadano%2FCM_Tramite_FA%2FPCIU_fichaTramite&vest=1331802501621 | K13: Tramitación Electrónica | L13: Certificado electrónico, DNI electrónico
A14: ='ES-PT Proposal'!A19 -> 18 | B14: 219231 | C14: Registro de Agentes Inmobiliarios de Cataluña | D14: El Registro de Agentes Inmobiliarios de Cataluña es público, tiene naturaleza administrativa y es de carácter obligatorio. La inscripción: Otorga la condición de agente inmobiliario homologado i da el derecho de hacer pública esta condición. Permite acreditar que la persona que figura en el Registro reúne los requisitos y condiciones adecuados para ejercer la actividad. Son agentes inmobiliarios las personas físicas o jurídicas que se dedican de manera habitual y retribuida a prestar servicios de mediación, asesoramiento y gestión en transacciones inmobiliarias con relación a operaciones de compraventa, alquiler, permuta o cesión de bienes inmuebles y los derechos correspondientes, incluyendo la constitución de estos derechos (artículo 55 de la Ley 18/2007, de 28 de diciembre, del derecho a la vivienda). La finalidad de este Registro es favorecer la transparencia en el sector de la vivienda y garantizar la protección de los consumidores. Garantiza a la ciudadania que el agente inmobiliario se encuentra con capacitat para dar un servicio eficiente y de calidad, ya que certifica que tiene una formación académica pertinente, experiencia en el ámbito en el que se desenvuelve y solvencia económica. | E14: registro de agentes inmobiliarios de cataluña, obligatorio, registro, ley | F14: Spanish | G14: Vivienda y Urbanismo | H14: Generalitat de Catalunya | I14: ESP_CMA_CATAL | J14: http://web.gencat.cat/redirect?uuid=ce209f4d-4060-11e4-81bd-cb94a8f4b18c&category=747fd95a-a82c-11e3-a972-000c29052e2c&idioma=es | K14: Descarga de formulario
A15: ='ES-PT Proposal'!A20 -> 19 | B15: 209380 | C15: COMUNICACION VENTAS EN LIQUIDACION | D15: Tramitar la comunicación de venta en liquidación | E15: comunicacion ventas en liquidacion | F15: Spanish | G15: * Comunicación * Economía, Comercio y Patrimonio de las Administraciones Públicas | H15: Comunidad Autónoma de Castilla-La Mancha | I15: ESP_CMA_CASTMANCHA | J15: http://www.jccm.es/sede/tramite/JPU | K15: Descarga y envío
A16: ='ES-PT Proposal'!A21 -> 20 | B16: 210076 | C16: Inscripción en el Registro especial de talleres de reparación de vehículos automóviles y de sus equipos y componentes | D16: Inscripción en el Registro de Talleres de Reparación de Automóviles a todos los talleres cuya actividad sea la de reparación tanto de vehículos como de piezas de los mismos. | E16: inscripción, registro, talleres, reparación, vehículos, automóviles, equipos, componentes, registro de talleres de reparación de automóviles | F16: Spanish | G16: Energía e industria | H16: Gobierno de La Rioja | I16: ESP_CMA_RIJ | J16: http://www.larioja.org/oficina-electronica/es?web=000&proc=06608 | K16: Descarga y envío
A17: ='ES-PT Proposal'!A22 -> 21 | B17: 213956 | C17: INSCRIPCIÓN REGISTRO OFICIAL DE CENTROS DE BRONCEADO DE LA COMUNIDAD AUTÓNOMA DE EXTREMADURA | D17: Inscripción de los establecimientos en los que se manipulen aparatos de bronceado mediante radiaciones ultravioletas. | E17: inscripción registro oficial de centros de bronceado de la comunidad autónoma de extremadura | F17: Spanish | G17: Salud | H17: Junta de Extremadura | I17: ESP_CMA_EXTRAMA | J17: https://ciudadano.gobex.es/buscador-de-tramites/-/tramite/ficha/5613 | K17: Descarga de formulario
A18: ='ES-PT Proposal'!A23 -> 22 | B18: 206916 | C18: Autorización sanitaria de los establecimientos de tatuaje y piercing de la Región de Murcia | D18: Regular en el ámbito territorial de la Región de Murcia los requisitos técnicos y condiciones sanitarias aplicables a los establecimientos no sanitarios donde se realizan prácticas de tatuaje, piercing u otros de naturaleza similar, con la finalidad de proteger la salud de los usuarios y de los trabajadores que las realizan | E18: sanitaria, autorización, establecimientos, tatuaje, piercing, región de murcia | F18: Spanish | G18: Salud | H18: Región de Murcia | I18: ESP_CMA_MURCIA | J18: http://www.carm.es/web/pagina?IDCONTENIDO=915&IDTIPO=240&RASTRO=c672$m2469 | K18: Descarga y envío
A19: ='ES-PT Proposal'!A26 -> 25 | B19: 210078 | C19: Solicitud de licencia de Gran Establecimiento Comercial Minorista | D19: Concesión de la licencia comercial para que establecimientos comerciales preexistentes puedan convertirse en grandes establecimientos comerciales, entendiéndose como tales aquellos que superen determinada superficie. | E19: licencia, solicitud, gran establecimiento comercial minorista | F19: Spanish | G19: Empresas | H19: Gobierno de La Rioja | I19: ESP_CMA_RIJ | J19: http://www.larioja.org/oficina-electronica/es?web=000&proc=06681 | K19: Descarga y envío
A20: ='ES-PT Proposal'!A4 -> 3 | B20: 221166 | C20: Ayudas para la realización de tesis doctorales | D20: Subvenciones destinadas a la formación del personal investigador dentro de programas oficiales de doctorado en Canarias (Modalidad A) | E20: ayudas, realización, tesis, doctorales, canarias, modalidad | F20: Spanish | G20: Tecnología, Investigación e Innovación | H20: Comunidad Autónoma de Canarias | I20: ESP_CMA_CANAR | J20: https://sede.gobcan.es/sede/tramites/4349 | K20: Tramitación electrónica
A21: ='ES-PT Proposal'!A5 -> 4 | B21: 287471 | C21: Matrícula- Automatrícula de Grado y Máster | D21: Acto por el que se inicia o se renueva anualmente la relación jurídica del estudiante con la Universidad en unos determinados estudios conducentes a la obtención de un título con validez en todo el territorio nacional. | E21: matrícula- automatrícula de grado, máster, universidad | F21: Spanish | G21: Educación y formación | H21: Universidad de Granada | I21: N/A | J21: http://ugr.es | K21: Tramitación Electrónica
A22: ='ES-PT Proposal'!A6 -> 5 | B22: 202057 | C22: Homologación de títulos universitarios y reconocimiento de cualificaciones | D22: A través de este procedimiento se puede solicitar la equivalencia de títulos de educación superior otorgados por instituciones extranjeras a titulación y a nivel académico de Grado o Máster universitarios oficiales en ramas de conocimiento y campos específicos. También permite la consulta del estado de su tramitación, tras cumplimentar la solicitud y presentarla en un registro oficial. | E22: títulos, homologación, universitarios, reconocimiento, cualificaciones, grado, máster | F22: Spanish | G22: Educación y formación | H22: Ministerio de Educacion, Cultura y Deporte | I22: ESP | J22: http://www.mecd.gob.es/servicios-al-ciudadano-mecd/catalogo/general/educacion/202057.html | K22: Tramitación Electrónica | L22: DNI electrónico, Usuario y contraseña,Cl@ve PIN
A23: ='ES-PT Proposal'!A7 -> 6 | B23: 994715 | C23: Modificación de datos de pensiones | D23: Poner en conocimiento de la Dirección General de Costes de Personal y Pensiones Públicas la variación de datos que tengan trascendencia en el cobro de la pensión o pensiones: estado civil, otras pensiones públicas, trabajo activo, opción entre pensiones incompatibles, etc. | E23: datos, modificación, pensiones, dirección general de costes de personal, pensiones públicas | F23: Spanish | G23: Servicios Sociales e Igualdad | H23: Ministerio de Hacienda y Función Pública | I23: ESP | J23: https://clasespasivas.gob.es/sitios/sedeclasespasivas/es-ES/solicitudElectronicaPrestaciones/Paginas/Registra.aspx | K23: Tramitación Electrónica | L23: Certificado electrónico, Cl@ve PIN,DNI electrónico
A24: ='ES-PT Proposal'!A12 -> 11 | B24: 997046 | C24: Importación, exportación, fabricación de medicamentos no registrados | D24: Importación, exportación, fabricación de medicamentos no registrados | E24: importación, exportación, fabricación, medicamentos, registrados | F24: Spanish | G24: * Obras Públicas, tráfico y transportes * Salud * Empresas | H24: Agencia Española de Medicamentos y Productos Sanitarios | I24: ESP | J24: https://sede.msssi.gob.es/ciudadanos/procAdministrativos.do?tipo=detallar&cod=997046 | K24: Tramitación Electrónica | L24: Usuario y contraseña, Certificado electrónico,DNI electrónico
A25: ='ES-PT Proposal'!A17 -> 16 | B25: 219601 | C25: Declaración de precios y servicios de los alojamientos turísticos | D25: Las personas titulares de los establecimientos de alojamiento turístico, tienen que declarar los servicios que ofrecen, así como los precios orientativos del establecimiento. Estos datos se publican en la Guía oficial de Establecimientos Turísticos a fin de garantizar la publicidad. | E25: precios, declaración, servicios, alojamientos, turísticos, guía, establecimientos turísticos | F25: Spanish | G25: Turismo, ocio y tiempo libre | H25: Generalitat de Catalunya | I25: ESP_CMA_CATAL | J25: http://web.gencat.cat/redirect?uuid=1377781b-4e89-11e4-8b57-3598f89ae6fa&category=772cf82a-a82c-11e3-a972-000c29052e2c&idioma=es | K25: Descarga de formulario
A26: ='ES-PT Proposal'!A24 -> 23 | B26: 214599 | C26: Cambio de actividad de local comercial | D26: Procedimiento de autorización de la solicitud del cambio de negocio a otro distinto del que se viniera ejerciendo en el local. | E26: actividad, cambio, local, comercial | F26: Spanish | G26: Vivienda y Urbanismo | H26: Comunidad de Madrid | I26: ESP_CMA_MAD | J26: http://www.madrid.org/cs/Satellite?c=CM_Tramite_FA&cid=1142564112542&definicion=Autorizacion+Licencia+Permiso+Carne&idConsejeria=1109266187248&idListConsj=1109265444710&idOrganismo=1109266227580&language=es&pagename=ComunidadMadrid%2FEstructura&sm=1109265843990&tipoServicio=CM_Tramite_FA | K26: Tramitación Electrónica
A27: ='ES-PT Proposal'!A25 -> 24 | B27: 205767 | C27: AUTORIZACIÓN DE FUNCIONAMIENTO DE SALÓN RECREATIVO O DE JUEGO | D27: Concesión de la autorización de funcionamiento para los locales que quieran funcionar como Salones Recreativos o Salones de Juego | E27: autorización de funcionamiento de salón recreativo o de juego, salones recreativos, salones de juego | F27: Spanish | G27: * Turismo, ocio y tiempo libre * Impuestos y otros tributos | H27: Gobierno de Aragón | I27: ESP_CMA_ARAGON | J27: https://gobierno.aragon.es/portal/site/GobiernoAragon/menuitem.bc635f27d1b850777f4dbc1754a051ca?vgnextoid=b0390eb4bb58b210VgnVCM100000450a15acRCRD&idTramite=1017 | K27: Descarga y envío
A28: ='ES-PT Proposal'!A27 -> 26 | B28: 992253 | C28: Inscripción y asignación Código Cuenta Cotización (CCC) | D28: Inscribir al empresario en la Seguridad Social mediante asignación del primer código cuenta cotización (CCC) o asignación de CCC secundarios a empresarios ya inscritos. | E28: inscripción, asignación, código cuenta cotización, ccc, seguridad social | F28: Spanish | G28: Empleo y Seguridad social | H28: Ministerio de Empleo y Seguridad Social | I28: ESP | J28: http://run.gob.es/yglfmk | K28: Tramitación Electrónica | L28: Certificado electrónico, DNI electrónico,Cl@ve permanente
A29: ='ES-PT Proposal'!A28 -> 27 | B29: 992224 | C29: Alta de trabajadores en el Régimen General | D29: Comunicación del inicio de prestación de servicios de trabajadores por cuenta ajena en el Régimen General de Seguridad Social | E29: trabajadores, régimen general, régimen general de seguridad social | F29: Spanish | G29: Empleo y Seguridad social | H29: Ministerio de Empleo y Seguridad Social | I29: ESP | J29: http://www.seg-social.es/Internet_1/Masinformacion/SistemaRed/ACCSRED/index.htm | K29: Proactivo | L29: Certificado electrónico, DNI electrónico
A30: ='ES-PT Proposal'!A29 -> 28 | B30: 997800 | C30: Modelo 200. IS. Impuesto sobre Sociedades e Impuesto sobre la Renta de no Residentes. Documentos de ingreso o devolución. (Modelo 200 y 206) | D30: Facilitar la presentación de la autoliquidación del Impuesto sobre Sociedades e Impuesto sobre la Renta de no Residentes (establecimientos permanentes y entidades en régimen de atribución de rentas constituidas en el extranjero con presencia en territorio español).Los obligados tributarios que deban tributar simultáneamente ante varias Administraciones (Hacienda estatal y Haciendas forales), deberán presentar autoliquidación ante la Hacienda estatal de la forma indicada y ante las Haciendas forales en los términos aprobados por éstas. | E30: 200, modelo, impuesto, sociedades, renta, residentes, ingreso, documentos, devolución, 206 | F30: Spanish | G30: Impuestos y otros tributos | H30: Agencia Estatal de Administracion Tributaria | I30: ESP | J30: https://www.agenciatributaria.gob.es/AEAT.sede/tramitacion/GE04.shtml | K30: Tramitación Electrónica | L30: Certificado electrónico
A31: ='ES-PT Proposal'!A30 -> 29 | B31: 992225 | C31: Baja de trabajadores en el Régimen General | D31: Comunicación del cese de la prestación de servicios de trabajadores por cuenta ajena del Régimen General | E31: trabajadores, baja, régimen general | F31: Spanish | G31: Empleo y Seguridad social | H31: Ministerio de Empleo y Seguridad Social | I31: ESP | J31: http://www.seg-social.es/Internet_1/Masinformacion/SistemaRed/ACCSRED/index.htm | K31: Proactivo | L31: Certificado electrónico, DNI electrónico
A32: ='ES-PT Proposal'!A31 -> 30 | B32: 992257 | C32: Ingreso cotizaciones Rég. General y asimilados | D32: Ingreso de cotizaciones por los responsables del pago del Régimen General y resto de regímenes por cuenta ajena. | E32: cotizaciones, ingreso, rég, general, asimilados, régimen general | F32: Spanish | G32: Empleo y Seguridad social | H32: Ministerio de Empleo y Seguridad Social | I32: ESP | J32: http://www.seg-social.es/Internet_1/Masinformacion/SistemaRed/ACCSRED/index.htm | K32: Tramitación Electrónica | L32: DNI electrónico, Certificado electrónico

Sheet ES_PS-en
A1: ES-PT Proposal | B1: Public Service | H1: Public Organization | J1: Channel | L1: Event | P1: Other
A2: Service Id. | B2: Identifier | C2: Name | D2: Description | E2: Keyword | F2: Language | G2: Thematic Area | H2: Preferred Label | I2: Spatial Code | J2: Identifier | K2: Type | L2: Id. | M2: Name | N2: Class | O2: Type | P2: eId Systems
A3: ='ES-PT Proposal'!A2 -> 1 | B3: 109000 | C3: ='ES-PT Proposal'!D2 -> Bithday Certificate | D3: The birth certificate is the document issued by the registrar of the corresponding Civil or Consular Registry, which attests to the fact of the birth, date on which it took place, sex and, in its case, time of the birth and affiliation. Likewise, electronic birth certificates may be issued with an electronic stamp of the General Directorate of Registries and Notaries with the data contained in the central database of persons registered in the Civil Registries. How? Enter the Electronic Office of the Ministry of Justice and access the Birth Certificate. You can choose to receive the certificate by postal mail at the address indicated in the application or pick it up in the corresponding Civil Registry that you expressly indicate. In this case the Civil Registry will tell you the date from which you can collect it from. | E3: birth, certificate, ministry of justice, civil registrar, consular, general directorate of registries, notarized, civil registries, electronic office of the Ministry of Justice, civil registry | F3: Spanish | G3: Justice | H3: Ministry of Justice | I3: ESP | J3: http://www.mjusticia.gob.es/cs/Satellite/Portal/es/servicios-ciudadano/tramites-gestiones-personales/certificadocertificacion | K3: Electronic processing | L3: http://administracion.gob.es/pagFront/tramites/miVidaEnTramites/listadoHechosVitales/previsualizacionHechoVital.htm?idHechoVital=21 | M3: Guide to administratives procedures when you have a child | N3: Life Event | O3: Having a child | P3: Electronic Certificate, Electronic National ID (DNIe), Others
A4: ='ES-PT Proposal'!A3 -> 2 | B4: 994455 | C4: ='ES-PT Proposal'!D3 -> Residence Certificate for Europeans | D4: Evidence of periods of legal residence in Spain for other bodies (Electronic Register of the National Police Body is ONLY admitted for citizens of Member States of the European Union, the European Economic Area, Switzerland and the Principality of Andorra) | E4: resident, certified, spain, electronic record of the national police body only, states, european union, european economic space, switzerland, principality of andorra | F4: Spanish | G4: Citizenship and Nationality | H4: Ministerio del Interior | I4: ESP | J4: https://sede.policia.gob.es/portalCiudadano/extranjeria/pr_cer_residen.html | K4: Electronic processing | P4: Electronic Certificate
A5: ='ES-PT Proposal'!A8 -> 7 | B5: 203557 | C5: ='ES-PT Proposal'!D8 -> Application for European Health Insurance Card | D5: Application for the European Health Card (EHC). The EHC is the document that accredits the right to access public health services during temporary stays in the Member States of the European Union, European Economic Area and Switzerland, under the same conditions and to the same extent as the citizens of the country you are visiting.This card is personal and non-transferable. The EHC will be valid for two years for both members and beneficiaries | E5: socialization, european health card, ehc, member state of the european union, european economic space, switzerland | F5: Spanish | G5: Health | H5: Mutualidad General de Funcionarios Civiles del Estado (MUFACE) | I5: ESP | J5: https://sede.muface.gob.es | K5: Electronic processing | P5: User and password, Electronic Certificate, Electronic National ID (DNIe)
A6: ='ES-PT Proposal'!A9 -> 8 | B6: 200265 | C6: ='ES-PT Proposal'!D9 -> Communication of change of address | D6: This service allows citizens, after their registration, to communicate their change of address to different bodies of the General State Administration, such as the General Directorate of Traffic, the Tax Agency, the General Directorate of the Police and Social Security, among others, without have to go in person to each of them. | E6: communication service of change of address, general state administration, general directorate of traffic, tax agency, general directorate of the police, social security | F6: Spanish | G6: * Relations between the citizen, company or public employee and the Administration * Citizen participation and initiatives | H6: S.Gral. de Administración Digital | I6: ESP | J6: https://cambiodomicilio.redsara.es/pcd/ | K6: Electronic processing | L6: http://administracion.gob.es/pagFront/tramites/miVidaEnTramites/listadoHechosVitales/previsualizacionHechoVital.htm?idHechoVital=103 | M6: Guide to administratives procedures when you buy a house | N6: Life Event | O6: Buying a house | P6: Electronic Certificate, Electronic National ID (DNIe)
A7: ='ES-PT Proposal'!A10 -> 9 | B7: 20650 | C7: ='ES-PT Proposal'!D10 -> Claiming retirement pension | D7: Access this service to request retirement economic benefit | E7: retirement, pension | F7: Spanish | G7: Pensions | H7: Instituto Nacional de la Seguridad Social | I7: ESP | J7: https://sede.seg-social.gob.es/Sede_1/ServiciosenLinea/Ciudadanos/index.htm?ssUserText=131145 | K7: Electronic processing | P7: Electronic Certificate
A8: ='ES-PT Proposal'!A11 -> 10 | B8: 203508 | C8: ='ES-PT Proposal'!D11 -> Instalación de situados para ejercer la venta ambulante | D8: The sale can be made in periodic or occasional markets, markets of singular regime, sectorial markets and isolated enclaves in the public road during the periods indicated by each authorization. | E8: located, installation, exercise, sale, ambulant | F8: Spanish | G8: Environment | H8: Ayuntamiento de Madrid | I8: - no spatial code - | J8: https://sede.madrid.es/portal/site/tramites/menuitem.1f3361415fda829be152e15284f1a5a0/?vgnextoid=59628af352bed010VgnVCM1000000b205a0aRCRD&vgnextchannel=f47ea38813180210VgnVCM100000c90da8c0RCRD | K8: Download and submittion
A9: ='ES-PT Proposal'!A13 -> 12 | B9: 203888 | C9: ='ES-PT Proposal'!D13 -> Authorization request for operating Fish Farms or Aquaculture Facilities | D9: Obtain the authorization for the start-up of fish farms or continental aquaculture facilities with a capacity of less than 500 tons. This authorization must be understood without prejudice to the concession that must be obtained from the Hydraulic Administration (Andalusian Water Agency or Guadalquivir Hydrographic Confederation). If the installation has a capacity greater than 500 tons, it is subject to AAU (section 9.9 of Annex I of the GICA). Competences in marine aquaculture and animal health control correspond to the Ministry responsible for agriculture and fisheries. | E9: implementation, operation of fish farms, aquaculture facilities, authorization, hydraulic administration, Andalusian water agency, Guadalquivir hydrographic confederation, aau, Annex I of the Gica, counseling | F9: Spanish | G9: Environment | H9: Junta de Andalucía | I9: ESP_CMA_ANDAL | J9: http://www.juntadeandalucia.es/haciendayadministracionpublica/ciudadania/web/guest/procedimientos | K9: Download and submittion
A10: ='ES-PT Proposal'!A14 -> 13 | B10: 220359 | C10: ='ES-PT Proposal'!D14 -> Authorization of commercial license to large commercial establishments and shopping centers. | D10: Authorize the granting of commercial license for the installation and opening, extension of usable space for exhibition and sale, transfer or change of activity to large retailers and shopping centers. | E10: license, authorization, commercial, large, establishments, centers | F10: Spanish | G10: Consumption | H10: Comunidad Autónoma de Canarias | I10: ESP_CMA_CANAR | J10: https://sede.gobcan.es/sede/tramites/2715 | K10: Downloadable form
A11: ='ES-PT Proposal'!A15 -> 14 | B11: 208249 | C11: ='ES-PT Proposal'!D15 -> Registry for startup of a guesthouse activity | D11: Registration in the General Register of Companies, Activities and Tourist Establishments of the Balearic Islands and in the Insular of Mallorca, of inn lodging establishments that develop their activity in the island of Mallorca. In the rest of the islands, the competent organs will be the respective Insular Councils. They are establishments that are part of a church, chapel or sanctuary allocating some of their dependencies to the accommodation service to the general public. The establishments owned by Public Administrations or private entities are excluded from this consideration where its use is reserved to groups of people who must meet certain requirements, such as belonging to a religious order or similar and, consequently, is not offered to the public in general. The holders of the hostel may have an admission regime and behavior standards according to the statutes of their religious order, which must be explicitly notified to potential guests before hiring | E11: start, registration, activity, establishment, lodging, guesthouse, general register of companies, activities, tourist establishments of the Illes Balears, insular de Mallorca | F11: Spanish | G11: Tourism, Leisure and Free time | H11: Gobierno de las Islas Baleares | I11: ESP_CMA_BALEAR | J11: https://www.caib.es/seucaib/es/tramites/tramite/2432054 | K11: Electronic processing
A12: ='ES-PT Proposal'!A16 -> 15 | B12: 215091 | C12: ='ES-PT Proposal'!D16 -> Communication of cessation of activity of a non-hotel tourist accommodation establishment | D12: Communicate the cessation of activity of a non-hotel tourist accommodation establishment to the Tourim Council. | E12: cessation, communication, activity, establishment, accommodation, tourism, non-hotel, council | F12: Spanish | G12: Tourism, Leisure and Free time | H12: Presidencia del Gobierno de Cantabria | I12: ESP_PR_CANTAB | J12: https://www.cantabria.es/tramites-web?codigo=IND-X-017 | K12: Download and submittion
A13: ='ES-PT Proposal'!A18 -> 17 | B13: 203212 | C13: ='ES-PT Proposal'!D18 -> Start of activity of catering facility | D13: Declaration of responsability for the start of the activity of tourist catering establishments in its various modalities (Restaurant, Cafeterias, Bars, Catering), as well as its subsequent modifications (changes of owner, cessation of activity, etc.) | E13: Start of activity of catering establishments, restaurant, cafeterias, bars | F13: Spanish | G13: * Tourism, Leisure and Free time * Business | H13: Comunidad de Madrid | I13: ESP_CMA_MAD | J13: http://www.madrid.org/cs/Satellite?c=CM_Tramite_FA&cid=1142598088068&noMostrarML=true&pageid=1331802501637&pagename=PortalCiudadano%2FCM_Tramite_FA%2FPCIU_fichaTramite&vest=1331802501621 | K13: Electronic processing | L13: Certificado electrónico, DNI electrónico
A14: ='ES-PT Proposal'!A19 -> 18 | B14: 219231 | C14: ='ES-PT Proposal'!D19 -> Register of Real Estate Agents of Catalonia | D14: "The Register of Real Estate Agents of Catalonia is public, has administrative nature and is mandatory. The inscription: It grants the status of accredited real estate agent and gives the right to disclose this condition to the public. It allows to prove that the person that appears in the Registry meets the requirements and adequate conditions to carry out the activity. Real estate agents are natural or legal persons who regularly provide professional services of mediation, advice and management in transactions of sale, rental, exchange or transfer of real estates and the corresponding rights, including the constitution of these rights (article 55 of Law 18/2007, of December 28, of the right to housing). The purpose of this Registry is to promote transparency in the real estate sector and to guarantee consumer protection. It guarantees citizens that the real estate agent is able to provide an efficient and quality service, as it certifies that he has a relevant academic background, experience in the field and economic solvency. " | E14: Catalan real estate agent registry, mandatory, registration, law | F14: Spanish | G14: Housing and Urban Development | H14: Generalitat de Catalunya | I14: ESP_CMA_CATAL | J14: http://web.gencat.cat/redirect?uuid=ce209f4d-4060-11e4-81bd-cb94a8f4b18c&category=747fd95a-a82c-11e3-a972-000c29052e2c&idioma=es | K14: Downloadable form
A15: ='ES-PT Proposal'!A20 -> 19 | B15: 209380 | C15: ='ES-PT Proposal'!D20 -> Clearance sales communication | D15: Processing clearance sale communication | E15: clearance sale communication | F15: Spanish | G15: * Communication * Economy, Commerce and Patrimony of the Public Administrations | H15: Comunidad Autónoma de Castilla-La Mancha | I15: ESP_CMA_CASTMANCHA | J15: http://www.jccm.es/sede/tramite/JPU | K15: Download and submittion
A16: ='ES-PT Proposal'!A21 -> 20 | B16: 210076 | C16: ='ES-PT Proposal'!D21 -> Registration in the Special Register of Repair Shops for motor vehicles and their equipment and components | D16: Registration in the Registry of Car Repair Shops for all workshops whose activity is the repair of both vehicles and parts thereof. | E16: registration, workshops, repair, vehicles, automobiles, equipment, components, registration of car repair shops | F16: Spanish | G16: Energy and Industry | H16: Gobierno de La Rioja | I16: ESP_CMA_RIJ | J16: http://www.larioja.org/oficina-electronica/es?web=000&proc=06608 | K16: Download and submittion
A17: ='ES-PT Proposal'!A22 -> 21 | B17: 213956 | C17: ='ES-PT Proposal'!D22 -> Registration in the Official Register of tanning centers | D17: Registration of establishments in which tanning devices are handled by ultraviolet radiation. | E17: inscription registration of tanning centers of the Autonomous Community of Extremadura | F17: Spanish | G17: Health | H17: Junta de Extremadura | I17: ESP_CMA_EXTRAMA | J17: https://ciudadano.gobex.es/buscador-de-tramites/-/tramite/ficha/5613 | K17: Downloadable form
A18: ='ES-PT Proposal'!A23 -> 22 | B18: 206916 | C18: ='ES-PT Proposal'!D23 -> Sanitary authorization for tattoo and piercing establishments | D18: Regulate in the territorial area of the Region of Murcia the technical requirements and sanitary conditions applicable to non-sanitary establishments where tattooing, piercing or other similar practices are carried out, in order to protect the health of their users and workers | E18: sanitary, authorization, establishments, tattoo, piercing, region of murcia | F18: Spanish | G18: Health | H18: Región de Murcia | I18: ESP_CMA_MURCIA | J18: http://www.carm.es/web/pagina?IDCONTENIDO=915&IDTIPO=240&RASTRO=c672$m2469 | K18: Download and submittion
A19: ='ES-PT Proposal'!A26 -> 25 | B19: 210078 | C19: ='ES-PT Proposal'!D26 -> Business licence for large retail trade establishment | D19: Commercial license granting to allow pre-existing commercial establishments become large commercial establishments, understanding as such those that exceed certain surface. | E19: license, application, large retail store | F19: Spanish | G19: Business | H19: Gobierno de La Rioja | I19: ESP_CMA_RIJ | J19: http://www.larioja.org/oficina-electronica/es?web=000&proc=06681 | K19: Download and submittion
A20: ='ES-PT Proposal'!A4 -> 3 | B20: 221166 | C20: ='ES-PT Proposal'!D4 -> Study aids to produce doctoral thesis | D20: Aids for research staff training within official doctoral programs in the Canary Islands (Modality A) | E20: aids, realization, thesis, doctoral, canary, modality | F20: Spanish | G20: Technology, Research and Innovation | H20: Comunidad Autónoma de Canarias | I20: ESP_CMA_CANAR | J20: https://sede.gobcan.es/sede/tramites/4349 | K20: Electronic processing
A21: ='ES-PT Proposal'!A5 -> 4 | B21: 287471 | C21: ='ES-PT Proposal'!D5 -> Application for Grade or Master studies in Granada University | D21: Act for initiating or annually renewing the legal relationship between students and University in certain studies leading to the attainment of a title valid for the whole national territory. | E21: enrollment - self-enrollment degree, master's degree, university | F21: Spanish | G21: Education and training | H21: Universidad de Granada | I21: N/A | J21: http://ugr.es | K21: Electronic processing
A22: ='ES-PT Proposal'!A6 -> 5 | B22: 202057 | C22: ='ES-PT Proposal'!D6 -> Homologation of university degrees and recognition of qualifications | D22: Through this procedure you can request the equivalence of higher education degrees awarded by foreign institutions to Official Bachelor's or Master's degree incertains knowledge branches and fields. It also allows to check the status of its processing after presenting the application at an official register. | E22: certificate, homologation, university, recognition, qualifications, degree, master | F22: Spanish | G22: Education and training | H22: Ministerio de Educacion, Cultura y Deporte | I22: ESP | J22: http://www.mecd.gob.es/servicios-al-ciudadano-mecd/catalogo/general/educacion/202057.html | K22: Electronic processing | P22: User and password, Electronic National ID (DNIe), Cl@ve PIN
A23: ='ES-PT Proposal'!A7 -> 6 | B23: 994715 | C23: ='ES-PT Proposal'!D7 -> Modification of data about pension | D23: To inform the General Directorate of Personnel Costs and Public Pensions of the variation of data that have significance in a pension or pensions collection: civil status, other public pensions, active work, option between incompatible pensions, etc. | E23: data, modification, pensions, general directorate of personnel costs, public pensions | F23: Spanish | G23: Social services and Equality | H23: Ministerio de Hacienda y Función Pública | I23: ESP | J23: https://clasespasivas.gob.es/sitios/sedeclasespasivas/es-ES/solicitudElectronicaPrestaciones/Paginas/Registra.aspx | K23: Electronic processing | P23: Electronic Certificate, Electronic National ID (DNIe), Cl@ve PIN
A24: ='ES-PT Proposal'!A12 -> 11 | B24: 997046 | C24: ='ES-PT Proposal'!D12 -> Import, export, manufacturing of non-registered medicines | D24: Import, export, manufacturing of non-registered medicines | E24: import, export, manufacturing, medicines, registered | F24: Spanish | G24: * Public Works, traffic and transport * Health * Business | H24: Agencia Española de Medicamentos y Productos Sanitarios | I24: ESP | J24: https://sede.msssi.gob.es/ciudadanos/procAdministrativos.do?tipo=detallar&cod=997046 | K24: Electronic processing | P24: User and password, Electronic Certificate, Electronic National ID (DNIe)
A25: ='ES-PT Proposal'!A17 -> 16 | B25: 219601 | C25: ='ES-PT Proposal'!D17 -> Declaration of prices and services of tourist accommodation | D25: "The holders of tourist accommodation establishments have to declare the services they offer, as well as the prices of the establishment. These data are published in the Official Guide of Tourist Establishments in order to guarantee publicity. " | E25: prices, declaration, services, accommodations, tourist, guide, tourist establishmentss | F25: Spanish | G25: Tourism, Leisure and Free time | H25: Generalitat de Catalunya | I25: ESP_CMA_CATAL | J25: http://web.gencat.cat/redirect?uuid=1377781b-4e89-11e4-8b57-3598f89ae6fa&category=772cf82a-a82c-11e3-a972-000c29052e2c&idioma=es | K25: Downloadable form
A26: ='ES-PT Proposal'!A24 -> 23 | B26: 214599 | C26: ='ES-PT Proposal'!D24 -> Change of activity in business premises | D26: Autorization procedure for changing the business activity carried out at the premise. | E26: activity, change, premise, commercial | F26: Spanish | G26: Housing and Urban Development | H26: Comunidad de Madrid | I26: ESP_CMA_MAD | J26: http://www.madrid.org/cs/Satellite?c=CM_Tramite_FA&cid=1142564112542&definicion=Autorizacion+Licencia+Permiso+Carne&idConsejeria=1109266187248&idListConsj=1109265444710&idOrganismo=1109266227580&language=es&pagename=ComunidadMadrid%2FEstructura&sm=1109265843990&tipoServicio=CM_Tramite_FA | K26: Electronic processing
A27: ='ES-PT Proposal'!A25 -> 24 | B27: 205767 | C27: ='ES-PT Proposal'!D25 -> Business licence for arcade establishment | D27: Granting licence for premises operating as Gaming Hall or Amusement Arcades | E27: Granting, licence, Gaming Hall, Amusement Arcades | F27: Spanish | G27: * Tourism, Leisure and Free time * Taxes and other contributions | H27: Gobierno de Aragón | I27: ESP_CMA_ARAGON | J27: https://gobierno.aragon.es/portal/site/GobiernoAragon/menuitem.bc635f27d1b850777f4dbc1754a051ca?vgnextoid=b0390eb4bb58b210VgnVCM100000450a15acRCRD&idTramite=1017 | K27: Download and submittion
A28: ='ES-PT Proposal'!A27 -> 26 | B28: 992253 | C28: ='ES-PT Proposal'!D27 -> Employer registration in Social Security with tax account code | D28: Enroll the employer in Social Security by assigning the contribution account code (CCC) or CCC allocation. | E28: enrollment, assignment, contribution account code quote, ccc, social security | F28: Spanish | G28: Employment and Social Security | H28: Ministerio de Empleo y Seguridad Social | I28: ESP | J28: http://run.gob.es/yglfmk | K28: Electronic processing | P28: Electronic Certificate, Electronic National ID (DNIe), Cl@ve PIN
A29: ='ES-PT Proposal'!A28 -> 27 | B29: 992224 | C29: ='ES-PT Proposal'!D28 -> Registration of workers in the General Scheme | D29: Communication of the beginning of provision of services for employed workers in the General Social Security Scheme | E29: workers, general schema, general social security scheme | F29: Spanish | G29: Employment and Social Security | H29: Ministerio de Empleo y Seguridad Social | I29: ESP | J29: http://www.seg-social.es/Internet_1/Masinformacion/SistemaRed/ACCSRED/index.htm | K29: Proactive | P29: Electronic Certificate, Electronic National ID (DNIe)
A30: ='ES-PT Proposal'!A29 -> 28 | B30: 997800 | C30: ='ES-PT Proposal'!D29 -> Submmition of Corporate Tax (Model 200) | D30: Facilitate the submittion of Corporation Tax and Income Tax payment for Non-Residents (permanent establishments and entities under the regime of income attribution for abroad constituion with presence in the Spanish territory). Those taxpayers who must be taxed simultaneously by several Administrations (State Treasury and Regional Treasuries) must submit the payment to State Treasury as describe and to Regional Treasuries under the terms approved by them. | E30: 200, model, tax, companies, earning, residents, income, documents, return, 206 | F30: Spanish | G30: Taxes and other contributions | H30: Agencia Estatal de Administracion Tributaria | I30: ESP | J30: https://www.agenciatributaria.gob.es/AEAT.sede/tramitacion/GE04.shtml | K30: Electronic processing | P30: Electronic Certificate
A31: ='ES-PT Proposal'!A30 -> 29 | B31: 992225 | C31: ='ES-PT Proposal'!D30 -> Withdrawal of workers in the General Scheme | D31: Communication of the cessation of the provision of services for employed workers in the General Scheme | E31: workers, cessation, general scheme | F31: Spanish | G31: Employment and Social Security | H31: Ministerio de Empleo y Seguridad Social | I31: ESP | J31: http://www.seg-social.es/Internet_1/Masinformacion/SistemaRed/ACCSRED/index.htm | K31: Proactive | P31: Electronic Certificate, Electronic National ID (DNIe)
A32: ='ES-PT Proposal'!A31 -> 30 | B32: 992257 | C32: ='ES-PT Proposal'!D31 -> Payment of social security contributions for workers in the General Scheme | D32: Deposit of contributions by those responsible for the payment of the General Scheme and other schemes for employed workers | E32: contributions, deposit, general scheme, employed workers | F32: Spanish | G32: Employment and Social Security | H32: Ministerio de Empleo y Seguridad Social | I32: ESP | J32: http://www.seg-social.es/Internet_1/Masinformacion/SistemaRed/ACCSRED/index.htm | K32: Electronic processing | P32: Electronic Certificate, Electronic National ID (DNIe)
